odoo/addons/sale_order_priority/README.rst
odoo/addons/sale_order_priority/__init__.py
odoo/addons/sale_order_priority/__manifest__.py
odoo/addons/sale_order_priority/i18n/es.po
odoo/addons/sale_order_priority/i18n/it.po
odoo/addons/sale_order_priority/i18n/sale_order_priority.pot
odoo/addons/sale_order_priority/models/__init__.py
odoo/addons/sale_order_priority/models/sale_order.py
odoo/addons/sale_order_priority/models/sale_order_line.py
odoo/addons/sale_order_priority/models/stock_move.py
odoo/addons/sale_order_priority/readme/CONTRIBUTORS.md
odoo/addons/sale_order_priority/readme/DESCRIPTION.md
odoo/addons/sale_order_priority/static/description/icon.png
odoo/addons/sale_order_priority/static/description/index.html
odoo/addons/sale_order_priority/tests/__init__.py
odoo/addons/sale_order_priority/tests/test_sale_stock.py
odoo/addons/sale_order_priority/views/sale.xml
odoo_addon_sale_order_priority-18.0.1.0.0.2.dist-info/METADATA
odoo_addon_sale_order_priority-18.0.1.0.0.2.dist-info/WHEEL
odoo_addon_sale_order_priority-18.0.1.0.0.2.dist-info/top_level.txt
odoo_addon_sale_order_priority-18.0.1.0.0.2.dist-info/RECORD
